opentslm/__init__.py
opentslm/data.py
opentslm/logger.py
opentslm/model/__init__.py
opentslm/model/encoder/CNNTokenizer.py
opentslm/model/encoder/TimeSeriesEncoderBase.py
opentslm/model/encoder/TransformerCNNEncoder.py
opentslm/model/encoder/TransformerMLPEncoder.py
opentslm/model/encoder/__init__.py
opentslm/model/llm/OpenTSLM.py
opentslm/model/llm/OpenTSLMFlamingo.py
opentslm/model/llm/OpenTSLMSP.py
opentslm/model/llm/TimeSeriesFlamingoWithTrainableEncoder.py
opentslm/model/llm/TimeSeriesLLM.py
opentslm/model/llm/__init__.py
opentslm/model/projector/LinearProjector.py
opentslm/model/projector/MLPProjector.py
opentslm/model/projector/__init__.py
opentslm/model_config.py
opentslm/prompt/__init__.py
opentslm/prompt/full_prompt.py
opentslm/prompt/prompt.py
opentslm/prompt/prompt_with_answer.py
opentslm/prompt/text_prompt.py
opentslm/prompt/text_time_series_prompt.py
opentslm/time_series_datasets/QADataset.py
opentslm/time_series_datasets/TSQADataset.py
opentslm/time_series_datasets/__init__.py
opentslm/time_series_datasets/constants.py
opentslm/time_series_datasets/ecg_qa/ECGQACoTQADataset.py
opentslm/time_series_datasets/ecg_qa/ECGQADataset.py
opentslm/time_series_datasets/ecg_qa/README.md
opentslm/time_series_datasets/ecg_qa/__init__.py
opentslm/time_series_datasets/ecg_qa/dataset_distribution.png
opentslm/time_series_datasets/ecg_qa/ecg_example_real.png
opentslm/time_series_datasets/ecg_qa/ecgqa_cot_loader.py
opentslm/time_series_datasets/ecg_qa/ecgqa_loader.py
opentslm/time_series_datasets/ecg_qa/example_prompt.md
opentslm/time_series_datasets/ecg_qa/plot_example.py
opentslm/time_series_datasets/har_cot/HARAccQADataset.py
opentslm/time_series_datasets/har_cot/HARCoTQADataset.py
opentslm/time_series_datasets/har_cot/__init__.py
opentslm/time_series_datasets/har_cot/har_cot_loader.py
opentslm/time_series_datasets/m4/M4QADataset.py
opentslm/time_series_datasets/m4/__init__.py
opentslm/time_series_datasets/m4/m4_loader.py
opentslm-0.1.0.dist-info/WHEEL
opentslm-0.1.0.dist-info/METADATA
opentslm-0.1.0.dist-info/RECORD
