Metadata-Version: 2.4
Name: opentslm
Version: 0.1.0
Summary: OpenTSLM: Open Time Series Language Model - Curriculum Learning for Multimodal Time Series Understanding with Large Language Models
Keywords: time-series,large-language-models,curriculum-learning,multimodal,healthcare
Author: Patrick Langer, Thomas Kaar, Max Rosenblattl, Maxwell A. Xu, Winnie Chow, Martin Maritsch, Robert Jakob, Aradhana Verma, Brian Han, Daniel Seung Kim, Henry Chubb, Scott Ceresnak, Aydin Zahedivash, Alexander Tarlochan Singh Sandhu, Fatima Rodriguez, Daniel McDuff, Elgar Fleisch, Oliver Aalami, Filipe Barata, Paul Schmiedmayer
License-Expression: MIT
Requires-Dist: numpy>=1.21
Requires-Dist: pandas>=1.3
Requires-Dist: torch>=2.0
Requires-Dist: tqdm>=4.62
Requires-Dist: matplotlib>=3.3
Requires-Dist: scikit-learn>=1.0
Requires-Dist: transformers>=4.25
Requires-Dist: huggingface-hub>=0.16
Requires-Dist: datasets>=2.0
Requires-Dist: peft>=0.4
Requires-Dist: requests>=2.28
Requires-Dist: einops>=0.6
Requires-Dist: wfdb>=4.0
Requires-Dist: open-flamingo>=0.0.2
Requires-Python: >=3.12
Project-URL: Bug Tracker, https://github.com/StanfordBDHG/OpenTSLM/issues
Project-URL: Homepage, https://opentslm.com
Project-URL: Repository, https://github.com/StanfordBDHG/OpenTSLM
